qyrusai/__init__.py
qyrusai/_clients.py
qyrusai/_exceptions.py
qyrusai/_rest.py
qyrusai/_types.py
qyrusai/configs.py
qyrusai/api_assertions/__init__.py
qyrusai/api_assertions/all_assertions.py
qyrusai/api_assertions/headers.py
qyrusai/api_assertions/json_body.py
qyrusai/api_assertions/json_path.py
qyrusai/api_assertions/json_schema.py
qyrusai/api_builder/__init__.py
qyrusai/api_builder/api_builder.py
qyrusai/base/__init__.py
qyrusai/base/base.py
qyrusai/data_amplifier/__init__.py
qyrusai/data_amplifier/data_amplifier.py
qyrusai/llm_evaluator/__init__.py
qyrusai/llm_evaluator/evaluator.py
qyrusai/nova/__init__.py
qyrusai/nova/nova.py
qyrusai/vision_nova/__init__.py
qyrusai/vision_nova/vision_nova.py
tests/__init__.py
tests/test_all_services.py
tests/test_api_builder.py
tests/test_data_amplifier.py
tests/test_functions.py
tests/test_rally.py
qyrusai-1.0.1.dist-info/METADATA
qyrusai-1.0.1.dist-info/WHEEL
qyrusai-1.0.1.dist-info/top_level.txt
qyrusai-1.0.1.dist-info/RECORD
