Metadata-Version: 2.4
Name: qyrusai
Version: 1.0.1
Summary: Qyrus AI SDK
Home-page: 
Author: Qyrus Inc
Author-email: support@qyrus.com
Requires-Python: >=3.7
Requires-Dist: httpx==0.25.0
Requires-Dist: pydantic==2.4.2
Requires-Dist: fastapi==0.111.0
Dynamic: author
Dynamic: author-email
Dynamic: description
Dynamic: description-content-type
Dynamic: requires-dist
Dynamic: requires-python
Dynamic: summary
